gcloud/aio/py.typed
gcloud/aio/storage/__init__.py
gcloud/aio/storage/blob.py
gcloud/aio/storage/bucket.py
gcloud/aio/storage/constants.py
gcloud/aio/storage/py.typed
gcloud/aio/storage/storage.py
gcloud/py.typed
gcloud_aio_storage-9.1.0.dist-info/LICENSE
gcloud_aio_storage-9.1.0.dist-info/METADATA
gcloud_aio_storage-9.1.0.dist-info/WHEEL
gcloud_aio_storage-9.1.0.dist-info/RECORD
