Metadata-Version: 2.1
Name: gcloud-aio-storage
Version: 9.1.0
Summary: Python Client for Google Cloud Storage
Home-page: https://github.com/talkiq/gcloud-aio
License: MIT
Author: Vi Engineering
Author-email: voiceai-eng@dialpad.com
Requires-Python: >=3.8,<4.0
Classifier: Development Status :: 5 - Production/Stable
Classifier: Intended Audience :: Developers
Classifier: License :: OSI Approved :: MIT License
Classifier: Operating System :: OS Independent
Classifier: Programming Language :: Python :: 3
Classifier: Programming Language :: Python :: 3.8
Classifier: Programming Language :: Python :: 3.9
Classifier: Programming Language :: Python :: 3.10
Classifier: Programming Language :: Python :: 3.11
Classifier: Programming Language :: Python :: 3.12
Classifier: Topic :: Internet
Requires-Dist: aiofiles (>=0.6.0,<24.0.0)
Requires-Dist: gcloud-aio-auth (>=3.6.0,<6.0.0)
Requires-Dist: pyasn1-modules (>=0.2.1,<0.4.0)
Requires-Dist: rsa (>=3.1.4,<5.0.0)
Project-URL: Repository, https://github.com/talkiq/gcloud-aio
